{
  "spider": "./jar/fan.txt;md5;f6dd09061793aa1f499be0ffebaf5f67",
  "lives": [
    {"name": "migu","type": 0,"url": "https://gitee.com/dream-deve/migu_video/raw/main/interface.txt","playerType": 1,"ua": "okhttp/3.8.1","timeout": 20,"epg": "https://epg.112114.xyz/?ch={name}&date={date}","logo": "https://epg.112114.xyz/logo/{name}.png"},
    {"name": "fmm","type": 0,"url": "https://live.fanmingming.com/tv/m3u/ipv6.m3u","playerType": 1,"ua": "okhttp/3.8.1","timeout": 20,"epg": "https://epg.112114.xyz/?ch={name}&date={date}","logo": "https://epg.112114.xyz/logo/{name}.png"},
    {"name": "live","type": 0,"url": "https://epg.pw/test_channels.m3u","playerType": 1,"ua": "okhttp/3.8.1","timeout": 20,"epg": "https://epg.112114.xyz/?ch={name}&date={date}","logo": "https://epg.112114.xyz/logo/{name}.png"},
    {"name": "ipv6","type": 0,"url": "./tvboxtv.txt","playerType": 1,"ua": "okhttp/3.8.1","timeout": 20,"epg": "https://epg.112114.xyz/?ch={name}&date={date}","logo": "https://epg.112114.xyz/logo/{name}.png"}
  ],
  "wallpaper": "https://jianbian.chuqiuyu.workers.dev",
  "sites": [
    {"key": "drpy_js_иұҶз“Ј","name": "жҗңзҙў | иұҶз“Ј[js]","type": 3,"api": "./lib/drpy2.min.js","ext": "./js/drpy.js","searchable": 1,"quickSearch": 0,"changeable": 0},
    {"key": "drpy_js_TVBдә‘ж’ӯ","name": "еҪұи§Ҷ | TVBдә‘ж’ӯ[js]","type": 3,"api": "./lib/drpy2.min.js","ext": "./js/TVBдә‘ж’ӯ.js","header": {"User-Agent": "Mozilla/5.0 (Windows NT 10.0; Win64; x64) AppleWebKit/537.36 (KHTML, like Gecko) Chrome/136.0.0.0 Safari/537.36 Edg/136.0.0.0"}},
    {"key": "й—Әйӣ·","name": "й—Әйӣ·в”ғMP4","type": 3,"api": "./FTY/drpy2.min.js","ext": "./js/678.js","header": {"User-Agent": "Mozilla/5.0 (Windows NT 10.0; Win64; x64) AppleWebKit/537.36 (KHTML, like Gecko) Chrome/136.0.0.0 Safari/537.36 Edg/136.0.0.0"}},
    {"key": "fyyy","name": "йЈһе®ҮеҪұйҷў","type": 3,"api": "csp_XBPQ","searchable": 1,"quickSearch": 1,"filterable": 1,"changeable": 1,"ext": {"еҲҶзұ»url": "http://ntfeiyu.com/nt/{cateId}/area/{area}/by/{by}/class/{class}/lang/{lang}/page/{catePg}/year/{year}.html","еҲҶзұ»": "з”өеҪұ$1#з”өи§Ҷеү§$2#з»јиүә$3#еҠЁжј«$4"},"header": {"User-Agent": "Mozilla/5.0 (Windows NT 10.0; Win64; x64) AppleWebKit/537.36 (KHTML, like Gecko) Chrome/136.0.0.0 Safari/537.36 Edg/136.0.0.0"},"jar": "./jar/sx.jar;md5;6186f490eadf878ba5de21a7fa29e594"},
    {"key": "cbh","name": "иҢ¶жқҜзӢҗ","type": 3,"api": "csp_XBPQ","searchable": 1,"quickSearch": 1,"filterable": 1,"changeable": 1,"ext": {"еҲҶзұ»url": "https://www.bnjxjd.com/movie/{cateId}/area/{area}/by/{by}/class/{class}/lang/{lang}/page/{catePg}/year/{year}.html","еҲҶзұ»": "з”өеҪұ$fenlei1#з”өи§Ҷеү§$fenlei2#з»јиүә$fenlei3#еҠЁжј«$fenlei4"},"header": {"User-Agent": "Mozilla/5.0 (Windows NT 10.0; Win64; x64) AppleWebKit/537.36 (KHTML, like Gecko) Chrome/136.0.0.0 Safari/537.36 Edg/136.0.0.0"},"jar": "./jar/sx.jar;md5;6186f490eadf878ba5de21a7fa29e594"},
    {"key": "зғӯж’ӯеҪұи§Ҷ","name": "зғӯж’ӯпҪңAPP","type": 3,"api": "csp_AppRJ","searchable": 1,"quickSearch": 1,"filterable": 0,"ext": {"url": "http://v.rbotv.cn"},"jar": "./xiaosa/spider.jar;md5;68ac435cd241549c0607e611c2e09bd0"},
    {"key": "жөӘй…·еҪұи§Ҷ","name": "жөӘй…·пҪңAPP","type": 3,"api": "csp_AppRJ","searchable": 1,"quickSearch": 1,"filterable": 0,"ext": {"url": "http://v.lkuys.cn"},"jar": "./xiaosa/spider.jar;md5;68ac435cd241549c0607e611c2e09bd0"},
    {"key": "еҠ иҸІ","name": "еҠ иҸІдёЁAPP","type": 3,"quickSearch": 1,"api": "csp_AppQi","ext": {"url": "","site": "https://aysappto.oss-cn-chengdu.aliyuncs.com/qj1.txt","dataKey": "dksvndkaAjekakcE","dataIv": "dksvndkaAjekakcE","deviceId": "","version": "","ua": ""},"jar": "./xiaosa/spider.jar;md5;68ac435cd241549c0607e611c2e09bd0"},
    {"key": "е’–е•Ў","name": "е’–е•ЎдёЁAPP","type": 3,"quickSearch": 1,"api": "csp_AppQi","ext": {"url": "","site": "https://daen-1256234123.cos.ap-shanghai.myqcloud.com/MuQi/mqxh.txt","dataKey": "37kj83zs1q16jk6t","dataIv": "37kj83zs1q16jk6t","deviceId": "","version": "101","ua": ""},"jar": "./xiaosa/spider.jar;md5;68ac435cd241549c0607e611c2e09bd0"},
    {"key": "е“”ж»ҙ","name": "е“”ж»ҙдёЁAPP","type": 3,"quickSearch": 1,"api": "csp_AppQi","ext": {"url": "","site": "https://ooxooxooxooxoo-1259561579.cos.ap-chengdu.myqcloud.com/ip.json","dataKey": "5ae8ee4bb95ea0ce","dataIv": "5ae8ee4bb95ea0ce","deviceId": "","version": "120","ua": "okhttp/3.10.0 BDYS/109.0.0.8"},"jar": "./xiaosa/spider.jar;md5;68ac435cd241549c0607e611c2e09bd0"},
    {"key": "иӢҘйӣӘ","name": "иӢҘйӣӘдёЁAPP","type": 3,"quickSearch": 1,"api": "csp_AppQi","ext": {"url": "https://appcms.rx4k.top","site": "","dataKey": "ZX10ysTYZWtIJCTU","dataIv": "ZX10ysTYZWtIJCTU","deviceId": "","version": "120"},"jar": "./xiaosa/spider.jar;md5;68ac435cd241549c0607e611c2e09bd0"},
    {"key": "и“қй№°","name": "и“қй№°пҪңAPP","type": 3,"quickSearch": 1,"api": "csp_AppQi","ext": {"url": "","site": "https://lanyinghz.oss-cn-hangzhou.aliyuncs.com/lanyingxmy.txt","dataKey": "ca94b06ca359d80e","dataIv": "ca94b06ca359d80e","deviceId": "","version": "120"},"jar": "./xiaosa/spider.jar;md5;68ac435cd241549c0607e611c2e09bd0"},
    {"key": "д»“йј ","name": "д»“йј пҪңAPP","type": 3,"quickSearch": 1,"api": "csp_AppQi","ext": {"url": "","site": "https://ceshi307386.oss-cn-beijing.aliyuncs.com/ceshi421.txt","dataKey": "da61247f5b662597","dataIv": "da61247f5b662597","deviceId": "","version": "120"},"jar": "./xiaosa/spider.jar;md5;68ac435cd241549c0607e611c2e09bd0"},
    {"key": "йІёйұј","name": "йІёйұјпҪңAPP","type": 3,"quickSearch": 1,"api": "csp_AppQi","ext": {"url": "","site": "https://jingyu4k-1312635929.cos.ap-nanjing.myqcloud.com/1.json","dataKey": "AAdgrdghjfgswerA","dataIv": "AAdgrdghjfgswerA","deviceId": "","version": ""},"jar": "./xiaosa/spider.jar;md5;68ac435cd241549c0607e611c2e09bd0"},
    {"key": "зғӯеү§","name": "зғӯеү§дёЁAPP","type": 3,"quickSearch": 1,"api": "csp_AppQi","ext": {"url": "https://www.rebovod.com","site": "","dataKey": "8191A7F47B37882F","dataIv": "8191A7F47B37882F","deviceId": "","version": "","ua": ""},"jar": "./xiaosa/spider.jar;md5;68ac435cd241549c0607e611c2e09bd0"},
    {"key": "еҪұи§Ҷ","name": "еҪұи§ҶдёЁAPP","type": 3,"quickSearch": 1,"api": "csp_AppQi","ext": {"url": "","site": "https://aysappto.oss-cn-chengdu.aliyuncs.com/qj2.txt","dataKey": "sada21321sdq231d","dataIv": "sada21321sdq231d","deviceId": "","version": "","ua": ""},"jar": "./xiaosa/spider.jar;md5;68ac435cd241549c0607e611c2e09bd0"},
    {"key": "е°ҸзҢӘ","name": "е°ҸзҢӘдёЁAPP","type": 3,"quickSearch": 1,"api": "csp_AppQi","ext": {"url": "","site": "https://tiantangyoulu.oss-cn-beijing.aliyuncs.com/tengxunyun.txt","dataKey": "seb5tq9mykp2w9ry","dataIv": "seb5tq9mykp2w9ry","deviceId": "","version": "","ua": "okhttp/3.10.0"},"jar": "./xiaosa/spider.jar;md5;68ac435cd241549c0607e611c2e09bd0"},
    {"key": "дә‘дә‘","name": "дә‘дә‘дёЁAPP","type": 3,"quickSearch": 1,"api": "csp_AppQi","ext": {"url": "","site": "https://staraugust123456.oss-cn-hangzhou.aliyuncs.com/2.txt","dataKey": "staraugust123456","dataIv": "staraugust123456","deviceId": "","version": "120","ua": ""},"jar": "./xiaosa/spider.jar;md5;68ac435cd241549c0607e611c2e09bd0"},
    {"key": "е…«еӨ©","name": "е…«еӨ©дёЁAPP","type": 3,"quickSearch": 1,"api": "csp_AppGet","ext": {"url": "https://dy.8ttv.cn","site": "","dataKey": "1111111111111111","dataIv": "1111111111111111","deviceId": "","version": "","ua": ""},"jar": "./xiaosa/spider.jar;md5;68ac435cd241549c0607e611c2e09bd0"},
    {"key": "зҙ«йҮ‘","name": "зҙ«йҮ‘дёЁAPP","type": 3,"quickSearch": 1,"api": "csp_AppGet","ext": {"url": "http://www.zjcvod.com","site": "","dataKey": "ab4e9a421675f14b","dataIv": "ab4e9a421675f14b","deviceId": "","version": "","ua": ""},"jar": "./xiaosa/spider.jar;md5;68ac435cd241549c0607e611c2e09bd0"},
    {"key": "еҲ·еү§","name": "еҲ·еү§дёЁAPP","type": 3,"quickSearch": 1,"api": "csp_AppGet","ext": {"url": "","site": "https://dingchaowangzhan.oss-cn-beijing.aliyuncs.com/1.txt","dataKey": "1387006363333333","dataIv": "1387006363333333","deviceId": "","version": "","ua": ""},"jar": "./xiaosa/spider.jar;md5;68ac435cd241549c0607e611c2e09bd0"},
    {"key": "д№қйӣ¶","name": "д№қйӣ¶дёЁAPP","type": 3,"quickSearch": 1,"api": "csp_AppGet","ext": {"url": "https://65fs2d9awaa1d2a7ea8.019990.xyz","site": "","dataKey": "5a9w6x58dsq6z3a6","dataIv": "5a9w6x58dsq6z3a6","deviceId": "","version": "","ua": ""},"jar": "./xiaosa/spider.jar;md5;68ac435cd241549c0607e611c2e09bd0"},
    {"key": "зұіеҘҮ","name": "зұіеҘҮдёЁAPP","type": 3,"quickSearch": 1,"api": "csp_AppGet","ext": {"url": "http://www.milkidc.cn","site": "","dataKey": "20c79c979da8db0f","dataIv": "20c79c979da8db0f","deviceId": "","version": "","ua": ""},"jar": "./xiaosa/spider.jar;md5;68ac435cd241549c0607e611c2e09bd0"},
    {"key": "жҳҹжҳҹ","name": "жҳҹжҳҹдёЁAPP","type": 3,"quickSearch": 1,"api": "csp_AppGet","ext": {"url": "http://starani.qcanime.xyz","site": "","dataKey": "123456789StarAni","dataIv": "123456789StarAni","deviceId": "","version": "","ua": "okhttp/3.10.0 BDYS/109.0.0.8"},"jar": "./xiaosa/spider.jar;md5;68ac435cd241549c0607e611c2e09bd0"},
    {"key": "еғҸзҙ ","name": "еғҸзҙ дёЁAPP","type": 3,"quickSearch": 1,"api": "csp_AppGet","ext": {"url": "https://mcvod.top","site": "","dataKey": "cnmbknmbtounimab","dataIv": "cnmbknmbtounimab","deviceId": "","version": "","ua": ""},"jar": "./xiaosa/spider.jar;md5;68ac435cd241549c0607e611c2e09bd0"},
    {"key": "иұҶдёҒ","name": "иұҶдёҒдёЁAPP","type": 3,"quickSearch": 1,"api": "csp_AppGet","ext": {"url": "http://45.66.157.77:9427","site": "","dataKey": "Xasdasd!123123dd","dataIv": "Xasdasd!123123dd","deviceId": "","version": "","ua": ""},"jar": "./xiaosa/spider.jar;md5;68ac435cd241549c0607e611c2e09bd0"},
    {"key": "зЁҖйҘӯ","name": "зЁҖйҘӯдёЁAPP","type": 3,"quickSearch": 1,"api": "csp_AppGet","ext": {"url": "https://app.xifanys.com","site": "","dataKey": "HM6Ly9yeS4ya3dvL","dataIv": "HM6Ly9yeS4ya3dvL","deviceId": "","version": "","ua": ""},"jar": "./xiaosa/spider.jar;md5;68ac435cd241549c0607e611c2e09bd0"},
    {"key": "еёғйӣ·","name": "еёғйӣ·дёЁAPP","type": 3,"quickSearch": 1,"api": "csp_AppGet","ext": {"url": "https://cms.bl4k.cc","site": "","dataKey": "B7uaxcwdpX2dww82","dataIv": "B7uaxcwdpX2dww82","deviceId": "","version": "","ua": ""},"jar": "./xiaosa/spider.jar;md5;68ac435cd241549c0607e611c2e09bd0"},
    {"key": "дә”е…«","name": "дә”е…«дёЁAPP","type": 3,"quickSearch": 1,"api": "csp_AppGet","ext": {"url": "https://dy.58ys.vip","site": "","dataKey": "JEWibY1AgWF0V1xx","dataIv": "JEWibY1AgWF0V1xx","deviceId": "","version": "","ua": ""},"jar": "./xiaosa/spider.jar;md5;68ac435cd241549c0607e611c2e09bd0"},
    {"key": "зӢӮдәә","name": "зӢӮдәәдёЁAPP","type": 3,"quickSearch": 1,"api": "csp_AppGet","ext": {"url": "https://www.zjkrmv.vip","site": "","dataKey": "vXeyuJFqTKqWUtWU","dataIv": "vXeyuJFqTKqWUtWU","deviceId": "","version": "","ua": ""},"jar": "./xiaosa/spider.jar;md5;68ac435cd241549c0607e611c2e09bd0"},
    {"key": "й©ҝз«ҷ","name": "й©ҝз«ҷдёЁAPP","type": 3,"quickSearch": 1,"api": "csp_AppGet","ext": {"url": "","site": "https://dyyztvappapigoodgx.68.gy:12689/ciwk28vu38io8/apiurl.txt","dataKey": "dyyztvapiappyyds","dataIv": "dyyztvapiappyyds","deviceId": "","version": "","ua": ""},"jar": "./xiaosa/spider.jar;md5;68ac435cd241549c0607e611c2e09bd0"},
    {"key": "еӨ–еү§","name": "еӨ–еү§дёЁAPP","type": 3,"quickSearch": 1,"api": "csp_AppGet","ext": {"url": "https://guowaiju.com","site": "","dataKey": "7xv16h7qgkrs9b1p","dataIv": "7xv16h7qgkrs9b1p","deviceId": "","version": "","ua": ""},"jar": "./xiaosa/spider.jar;md5;68ac435cd241549c0607e611c2e09bd0"},
    {"key": "зҲұеҪұ","name": "зҲұеҪұдёЁAPP","type": 3,"quickSearch": 1,"api": "csp_AppGet","ext": {"url": "https://app.lkdyw.cn","site": "","dataKey": "e65144389e9361b5","dataIv": "e65144389e9361b5","deviceId": "","version": "","ua": ""},"jar": "./xiaosa/spider.jar;md5;68ac435cd241549c0607e611c2e09bd0"},
    {"key": "зҒ«зӢҗ","name": "зҒ«зӢҗдёЁAPP","type": 3,"quickSearch": 1,"api": "csp_AppGet","ext": {"url": "http://huohu.yihn.cc","site": "","dataKey": "huohushipingetap","dataIv": "huohushipingetap","deviceId": "","version": "140","ua": ""},"jar": "./xiaosa/spider.jar;md5;68ac435cd241549c0607e611c2e09bd0"},
    {"key": "дә‘з«Ҝ","name": "дә‘з«ҜпҪңAPP","type": 3,"quickSearch": 1,"api": "csp_AppGet","ext": {"url": "https://c8k2n5l0i9s8b2m1jj8k2x2l9ff68.ydysapi.cfd:27899","site": "","dataKey": "k9o3p2c8b7m3z0o8","dataIv": "k9o3p2c8b7m3z0o8","deviceId": "","version": ""},"jar": "./xiaosa/spider.jar;md5;68ac435cd241549c0607e611c2e09bd0"},
    {"key": "иҺұзұі","name": "иҺұзұіпҪңAPP","type": 3,"quickSearch": 1,"api": "csp_AppGet","ext": {"url": "","site": "http://laiget-1313189639.cos.ap-guangzhou.myqcloud.com/laimi.txt","dataKey": "ce032244d093b3e2","dataIv": "ce032244d093b3e2","deviceId": "","version": ""},"jar": "./xiaosa/spider.jar;md5;68ac435cd241549c0607e611c2e09bd0"},
    {"key": "зҒөиҷҺ","name": "зҒөиҷҺпҪңAPP","type": 3,"quickSearch": 1,"api": "csp_AppGet","ext": {"url": "","site": "https://bind.315999.xyz/89.txt","dataKey": "#getapp@TMD@2025","dataIv": "#getapp@TMD@2025","deviceId": "","version": "120"},"jar": "./xiaosa/spider.jar;md5;68ac435cd241549c0607e611c2e09bd0"},
    {"key": "ж——жҳҹ","name": "ж——жҳҹпҪңAPP","type": 3,"quickSearch": 1,"api": "csp_AppGet","ext": {"url": "http://ys.qist.top","site": "","dataKey": "2SWSPFxugBLPPOKo","dataIv": "2SWSPFxugBLPPOKo","deviceId": "","version": "120"},"jar": "./xiaosa/spider.jar;md5;68ac435cd241549c0607e611c2e09bd0"},
    {"key": "дё«дё«","name": "дё«дё«пҪңAPP","type": 3,"quickSearch": 1,"api": "csp_AppGet","ext": {"url": "http://tv.yy-fun.cc","dataKey": "qkxnwkfjwpcnwycl","dataIv": "qkxnwkfjwpcnwycl","deviceId": "","version": ""},"jar": "./xiaosa/spider.jar;md5;68ac435cd241549c0607e611c2e09bd0"},
    {"key": "иҗқеҚң","name": "иҗқеҚңпҪңAPP","type": 3,"quickSearch": 1,"api": "csp_AppGet","ext": {"url": "https://apiapplbys.lbys.app:5678","dataKey": "apiapplbyskey168","dataIv": "apiapplbyskey168","deviceId": "","version": "107"},"jar": "./xiaosa/spider.jar;md5;68ac435cd241549c0607e611c2e09bd0"},
    {"key": "зұіе…”","name": "зұіе…”пҪңAPP","type": 3,"quickSearch": 1,"api": "csp_AppGet","ext": {"url": "https://new.tkbot.fun","dataKey": "d032c12876bc6848","dataIv": "d032c12876bc6848","deviceId": "","version": "200"},"jar": "./xiaosa/spider.jar;md5;68ac435cd241549c0607e611c2e09bd0"},
    {"key": "з§»еҠЁ","name": "з§»еҠЁпҪңAPP","type": 3,"api": "csp_YD","searchable": 1,"quickSearch": 1,"style": {"type": "list"},"jar": "./xiaosa/spider.jar;md5;68ac435cd241549c0607e611c2e09bd0"},
    {"key": "зҺ©еҒ¶","name": "рҹ‘ҪзҺ©еҒ¶е“Ҙе“Ҙв”ғ4Kеј№е№•","type": 3,"api": "csp_WoGGGuard","timeout": 30,"searchable": 1,"quickSearch": 1,"changeable": 0,"ext": {"Cloud-drive": "tvfan/Cloud-drive.txt","from": "4k|auto","siteUrl": "https://www.wogg.com/","danMu": "еј№"}},
    {"key": "YGP","name": "рҹҡҖеҸЁи§ӮиҚҗеҪұв”ғйў„е‘ҠзүҮ","type": 3,"api": "csp_YGPGuard","searchable": 0,"quickSearch": 0,"changeable": 0},
    {"key": "alllive","name": "рҹ“ҪпёҸдёҖзӣҙж’ӯв”ғзӣҙж’ӯ","type": 3,"api": "csp_AllliveGuard","playerType": 2,"searchable": 0,"quickSearch": 0,"changeable": 0},
    {"key": "seed","name": "рҹ’ЎиҒҡеү§еү§в”ғдёүзӣҳ","type": 3,"api": "csp_SeedhubGuard","changeable": 0,"ext": "5++kwLhNYm9UrO9wh7Dl7eKamTee4s/5","searchable": 1,"quickSearch": 1,"indexs": 0,"style": {"type": "list"}},
    {"key": "ж–ҮйҮҮ","name": "рҹ’®ж–ҮйҮҮв”ғз§’ж’ӯ","type": 3,"api": "csp_JpysGuard","timeout": 15,"playerType": 2,"searchable": 1,"quickSearch": 1,"changeable": 1},
    {"key": "еҺӮй•ҝ","name": "рҹ“”еҺӮй•ҝв”ғз§’ж’ӯ","type": 3,"api": "csp_NewCzGuard","timeout": 15,"playerType": 2,"searchable": 1,"quickSearch": 1,"changeable": 1},
    {"key": "зіҜзұі","name": "рҹҚ“зіҜзұів”ғз§’ж’ӯ","type": 3,"api": "csp_NmyswvGuard","timeout": 15,"searchable": 1,"quickSearch": 1,"changeable": 1},
    {"key": "жҜ”зү№","name": "рҹҚ„жҜ”зү№в”ғз§’ж’ӯ","type": 3,"api": "csp_BttwooGuard","timeout": 15,"searchable": 1,"quickSearch": 1,"changeable": 1},
    {"key": "з«Ӣж’ӯ","name": "рҹҢҹз«Ӣж’ӯв”ғз§’ж’ӯ","type": 3,"api": "csp_LibvioGuard","timeout": 15,"searchable": 1,"quickSearch": 1,"changeable": 1,"ext": {"Cloud-drive": "tvfan/Cloud-drive.txt","from": "4k|auto"}},
    {"key": "йІёйұј","name": "рҹ‘ҖйІёйұјв”ғз§’ж’ӯ","type": 3,"api": "csp_AppSxGuard","searchable": 1,"quickSearch": 1,"filterable": 1,"ext": "rfOX1voDIQhH8epBwpmIsuS/sSCZ183jzSI6L432F1wEM1kc4mV87fQxIbwNi40y4T/RKJAUnj9z8A=="},
    {"key": "еҺҹеҲӣ","name": "вҳҖеҺҹеҲӣв”ғдёҚеҚЎ","type": 3,"api": "csp_YCyzGuard","timeout": 30,"playerType": 1,"searchable": 1,"quickSearch": 1,"changeable": 1},
    {"key": "иӢ№жһң","name": "рҹҚҺиӢ№жһңв”ғдёҚеҚЎ","type": 3,"api": "csp_LiteAppleGuard","timeout": 15,"searchable": 1,"quickSearch": 1,"changeable": 1},
    {"key": "дҪҺз«Ҝ","name": "вҸ®пёҸдҪҺз«Ҝв”ғеӨ–еү§","type": 3,"api": "csp_DdrkGuard","timeout": 15,"playerType": "2","searchable": 1,"quickSearch": 1,"changeable": 1},
    {"key": "ж¬ўи§Ҷ","name": "рҹ‘“ж¬ўи§Ҷв”ғеӨҡзәҝ","type": 3,"api": "csp_AppTTGuard","timeout": 15,"playerType": 2,"searchable": 1,"quickSearch": 1,"changeable": 1,"ext": "uqGL1bNENExT9fFAy5mE5qU="},
    {"key": "зғӯж’ӯ","name": "рҹ“әзғӯж’ӯв”ғеӨҡзәҝ","type": 3,"api": "csp_AppTTGuard","timeout": 15,"playerType": 2,"searchable": 1,"quickSearch": 1,"changeable": 1,"ext": "uqGL1bNENExT7/hGxpSE5qU="},
    {"key": "дёӢйҘӯ","name": "рҹҚҷдёӢйҘӯв”ғеӨҡзәҝ","type": 3,"api": "csp_AppSxGuard","searchable": 1,"quickSearch": 1,"filterable": 1,"ext": "rfOX1voDIQhH8epBwpmIsuSlujLK3sriwSIhL5XjHg0adEYJpXZ48P0hOq5X1M8s5yKKbc1C2H4563JjH/01RZDAuqM="},
    {"key": "еҘҘзү№","name": "рҹҸқеҘҘзү№в”ғеӨҡзәҝ","type": 3,"api": "csp_AueteGuard","timeout": 15,"searchable": 1,"quickSearch": 1,"changeable": 1,"ext": "https://auete.com/"},
    {"key": "иҚҗзүҮ","name": "рҹҗӯиҚҗзүҮв”ғP2P","type": 3,"api": "csp_JPJGuard","timeout": 15,"playerType": 2,"searchable": 1,"quickSearch": 1,"changeable": 0},
    {"key": "ж–°6V","name": "рҹ§Іж–°6Vв”ғзЈҒеҠӣ","type": 3,"api": "csp_SixVGuard","timeout": 15,"searchable": 1,"quickSearch": 1,"changeable": 0,"ext": "https://www.xb6v.com/"},
    {"key": "Dm84","name": "рҹҡҢе·ҙеЈ«в”ғеҠЁжј«","type": 3,"api": "csp_Dm84Guard","timeout": 15,"searchable": 1,"quickSearch": 1,"changeable": 1},
    {"key": "Ysj","name": "рҹҺҖејӮз•Ңв”ғеҠЁжј«","type": 3,"api": "csp_YsjGuard","timeout": 15,"searchable": 1,"quickSearch": 1,"changeable": 1},
    {"key": "Anime1","name": "рҹҗҫж—Ҙжң¬в”ғеҠЁжј«","type": 3,"api": "csp_Anime1Guard","timeout": 15,"searchable": 1,"quickSearch": 1,"changeable": 1},
    {"key": "и¶…е…Ё","name": "вҡҪи¶…е…Ёв”ғзңӢзҗғ","type": 3,"api": "csp_ZbzGuard","searchable": 0,"quickSearch": 0,"changeable": 0,"style": {"type": "list"},"ext": "uqGL1fpJNAUf8fdTwZCE5qSp+Q=="},
    {"key": "88","name": "вҡҪ88в”ғзңӢзҗғ","type": 3,"api": "csp_Sir88Guard","timeout": 15,"searchable": 0,"changeable": 0,"style": {"type": "list"}},
    {"key": "зңӢзҗғ","name": "вҡҪжүӢжңәв”ғзңӢзҗғ","type": 3,"api": "csp_KanqiuGuard","timeout": 15,"searchable": 0,"changeable": 0,"style": {"type": "list"}},
    {"key": "MTV","name": "рҹҺ§жҳҺжҳҹв”ғMV","type": 3,"api": "csp_BiliGuard","style": {"type": "rect","ratio": 1.597},"searchable": 0,"quickSearch": 0,"changeable": 0,"ext": {"json": "https://nos.netease.com/ysf/5af5fbe12a88b7c45aa1c21e6551826c.txt"}},
    {"key": "иҷҺзүҷзӣҙж’ӯjs","name": "рҹҗҜиҷҺзүҷв”ғзӣҙж’ӯ","type": 3,"api": "https://gh-proxy.com/https://raw.githubusercontent.com/fantaiying7/EXT/refs/heads/main/drpy2.js","ext": "https://gh-proxy.com/https://raw.githubusercontent.com/fantaiying7/EXT/refs/heads/main/huya2.js","style": {"type": "rect","ratio": 1.755},"timeout": 15,"playerType": "2","searchable": 0,"quickSearch": 0,"changeable": 0},
    {"key": "ж–—йұјjs","name": "рҹҗҹж–—йұјв”ғзӣҙж’ӯ","type": 3,"api": "https://gh-proxy.com/https://raw.githubusercontent.com/fantaiying7/EXT/refs/heads/main/drpy2.min.js","ext": "https://gh-proxy.com/https://raw.githubusercontent.com/fantaiying7/EXT/refs/heads/main/ж–—йұјзӣҙж’ӯ.js","style": {"type": "rect","ratio": 1.755},"timeout": 15,"playerType": "2","searchable": 0,"quickSearch": 0,"changeable": 0},
    {"key": "жңүеЈ°е°ҸиҜҙ","name": "рҹҺ§жңүеЈ°в”ғе°ҸиҜҙ","type": 3,"api": "csp_Tingshu275Guard","searchable": 0,"quickSearch": 0,"changeable": 0},
    {"key": "Aid","name": "рҹҡ‘жҖҘж•‘в”ғж•ҷеӯҰ","type": 3,"api": "csp_FirstAidGuard","searchable": 0,"quickSearch": 0,"changeable": 0,"style": {"type": "rect","ratio": 3.8}},
    {"key": "жҠ жҗң","name": "рҹҚ„жҠ жҠ в”ғжҗңжҗң","type": 3,"api": "csp_KkSsGuard","searchable": 1,"quickSearch": 1,"changeable": 0,"ext": {"Cloud-drive": "tvfan/Cloud-drive.txt","from": "4k|auto"}},
    {"key": "UC","name": "рҹҢҲдјҳжұҗв”ғжҗңжҗң","type": 3,"api": "csp_UuSsGuard","searchable": 1,"quickSearch": 1,"changeable": 0,"ext": {"Cloud-drive": "tvfan/Cloud-drive.txt","from": "4k|auto"}},
    {"key": "push_agent","name": "рҹӣҙжүӢжңәв”ғжҺЁйҖҒ","type": 3,"api": "csp_PushGuard","searchable": 0,"quickSearch": 0,"ext": {"Cloud-drive": "tvfan/Cloud-drive.txt","from": "4k|auto"}},
    {"key": "Bili","name": "рҹ…ұе“”е“”еҗҲйӣҶв”ғеј№е№•","type": 3,"api": "csp_BiliGuard","style": {"type": "rect","ratio": 1.597},"searchable": 1,"quickSearch": 0,"changeable": 0,"ext": {"json": "https://nos.netease.com/ysf/0075389dca9afadd4614e9713765ff17.txt"}},
    {"key": "Biliych","name": "рҹ…ұе“”е“”жј”е”ұдјҡв”ғеј№е№•","type": 3,"api": "csp_BiliGuard","style": {"type": "rect","ratio": 1.597},"searchable": 1,"quickSearch": 0,"changeable": 0,"ext": {"json": "https://nos.netease.com/ysf/6496356286589c68f52c2f99c0c674c7.txt"}},
    {"key": "dr_е…”е°Ҹиҙқ","name": "рҹ“ҡе„ҝз«Ҙв”ғеҗҜи’ҷ","type": 3,"api": "https://gh-proxy.com/https://raw.githubusercontent.com/fantaiying7/EXT/refs/heads/main/drpy2.min.js","ext": "https://gh-proxy.com/https://raw.githubusercontent.com/fantaiying7/EXT/refs/heads/main/%E5%85%94%E5%B0%8F%E8%B4%9D.js","style": {"type": "rect","ratio": 1.597},"searchable": 0,"quickSearch": 0,"changeable": 0},
    {"key": "е°‘е„ҝж•ҷиӮІ","name": "рҹ“ҡе°‘е„ҝв”ғж•ҷиӮІ","type": 3,"api": "csp_BiliGuard","style": {"type": "rect","ratio": 1.597},"searchable": 0,"quickSearch": 0,"changeable": 0,"ext": {"json": "https://nos.netease.com/ysf/89370c8ddf36b5e1beb4d71adb921bda.txt"}},
    {"key": "е°ҸеӯҰиҜҫе Ӯ","name": "рҹ“ҡе°ҸеӯҰв”ғиҜҫе Ӯ","type": 3,"api": "csp_BiliGuard","style": {"type": "rect","ratio": 1.597},"searchable": 0,"quickSearch": 0,"changeable": 0,"ext": {"json": "https://nos.netease.com/ysf/d7a21cf34ede56f5c686ecfba5fc7e3f.txt"}},
    {"key": "еҲқдёӯиҜҫе Ӯ","name": "рҹ“ҡеҲқдёӯв”ғиҜҫе Ӯ","type": 3,"api": "csp_BiliGuard","style": {"type": "rect","ratio": 1.597},"searchable": 0,"quickSearch": 0,"changeable": 0,"ext": {"json": "https://nos.netease.com/ysf/8f55d520f8d70056695740ef151744a7.txt"}},
    {"key": "й«ҳдёӯж•ҷиӮІ","name": "рҹ“ҡй«ҳдёӯв”ғиҜҫе Ӯ","type": 3,"api": "csp_BiliGuard","style": {"type": "rect","ratio": 1.597},"searchable": 0,"quickSearch": 0,"changeable": 0,"ext": {"json": "https://nos.netease.com/ysf/c66a4b5356141c49fd45ec51568017b4.txt"}},
    {"key": "еҘҮдјҳ","name": "еҪұи§Ҷ | пёҸеҘҮдјҳ[зӣҙиҝһ]","type": 3,"api": "csp_XBPQ","searchable": 1,"quickSearch": 1,"filterable": 1,"ext": "./json/еҘҮдјҳ.json","jar": "./jar/Yoursmile.jar;md5;97796a79a781055669f2d5442439dc5f"},
    {"key": "йҮҸеӯҗ","name": "еҪұи§Ҷ | йҮҸеӯҗ[зӣҙиҝһ]","type": 1,"api": "https://cj.lziapi.com/api.php/provide/vod/","searchable": 1,"categories": ["еҠЁдҪңзүҮ","е–ңеү§зүҮ","зҲұжғ…зүҮ","з§‘е№»зүҮ","жҒҗжҖ–зүҮ","еү§жғ…зүҮ","жҲҳдәүзүҮ","еӣҪдә§еү§","йҰҷжёҜеү§","йҹ©еӣҪеү§","ж¬§зҫҺеү§","и®°еҪ•зүҮ","еҸ°ж№ҫеү§","ж—Ҙжң¬еү§","жө·еӨ–еү§","жі°еӣҪеү§","еӨ§йҷҶз»јиүә","жёҜеҸ°з»јиүә","ж—Ҙйҹ©з»јиүә","ж¬§зҫҺз»јиүә","еӣҪдә§еҠЁжј«","ж—Ҙйҹ©еҠЁжј«","ж¬§зҫҺеҠЁжј«","жёҜеҸ°еҠЁжј«","жө·еӨ–еҠЁжј«"]},
    {"key": "йқһеҮЎ","name": "еҪұи§Ҷ | йқһеҮЎ[зӣҙиҝһ]","type": 1,"api": "http://ffzy.tv/api.php/provide/vod/","searchable": 1,"categories": ["еҠЁдҪңзүҮ","е–ңеү§зүҮ","зҲұжғ…зүҮ","з§‘е№»зүҮ","жҒҗжҖ–зүҮ","еү§жғ…зүҮ","жҲҳдәүзүҮ","еӣҪдә§еү§","йҰҷжёҜеү§","йҹ©еӣҪеү§","ж¬§зҫҺеү§","и®°еҪ•зүҮ","еҸ°ж№ҫеү§","ж—Ҙжң¬еү§","жө·еӨ–еү§","жі°еӣҪеү§","еӨ§йҷҶз»јиүә","жёҜеҸ°з»јиүә","ж—Ҙйҹ©з»јиүә","ж¬§зҫҺз»јиүә","еӣҪдә§еҠЁжј«","ж—Ҙйҹ©еҠЁжј«","ж¬§зҫҺеҠЁжј«","жёҜеҸ°еҠЁжј«","жө·еӨ–еҠЁжј«"]},
    {"key": "зҙўе°ј","name": "еҪұи§Ҷ | зҙўе°ј[зӣҙиҝһ]","type": 0,"api": "https://suoniapi.com/api.php/provide/vod/at/xml/","searchable": 1,"categories": ["еҠЁдҪңзүҮ","е–ңеү§зүҮ","зҲұжғ…зүҮ","з§‘е№»зүҮ","жҒҗжҖ–зүҮ","еү§жғ…зүҮ","жҲҳдәүзүҮ","еӣҪдә§еү§","ж¬§зҫҺеү§","жёҜеү§","еҸ°еү§","йҹ©еү§","ж—Ҙеү§","жі°еү§","зәӘеҪ•зүҮ","жө·еӨ–еү§","еӨ§йҷҶз»јиүә","жёҜеҸ°з»јиүә","ж—Ҙйҹ©з»јиүә","ж¬§зҫҺз»јиүә","еӣҪдә§еҠЁжј«","ж—Ҙйҹ©еҠЁжј«","ж¬§зҫҺеҠЁжј«","жёҜеҸ°еҠЁжј«","жө·еӨ–еҠЁжј«","еҪұи§Ҷи§ЈиҜҙ"]},
    {"key": "еҚ§йҫҷиө„жәҗ","name": "еҪұи§Ҷ | еҚ§йҫҷиө„жәҗ[зӣҙиҝһ]","type": 1,"api": "https://wolongzyw.com/api.php/provide/vod/?ac=list","searchable": 1,"changeable": 1},
    {"key": "ikunиө„жәҗ","name": "еҪұи§Ҷ | ikunиө„жәҗ[зӣҙиҝһ]","type": 1,"api": "https://www.ikunzy.com/api.php/provide/vod/","searchable": 1,"categories": ["еҠЁдҪңзүҮ","е–ңеү§зүҮ","зҲұжғ…зүҮ","з§‘е№»зүҮ","жҒҗжҖ–зүҮ","еү§жғ…зүҮ","жҲҳдәүзүҮ","еӣҪдә§еү§","йҰҷжёҜеү§","еҸ°ж№ҫеү§","йҹ©еӣҪеү§","зәӘеҪ•зүҮ","еҠЁз”»зүҮ","ж—Ҙжң¬еү§","жі°еӣҪеү§","ж¬§зҫҺеү§","еӣҪдә§еҠЁжј«"," ж—Ҙжң¬еҠЁжј«","ж¬§зҫҺеҠЁжј«","жө·еӨ–еҠЁжј«","з”өеҪұи§ЈиҜҙ","еӨ§йҷҶз»јиүә","жёҜеҸ°з»јиүә","ж—Ҙйҹ©з»јиүә","ж¬§зҫҺз»јиүә"]},
    {"key": "Uй…·иө„жәҗйўЁ","name": "еҪұи§Ҷ | е°Өй…·[зӣҙиҝһ]","type": 1,"api": "https://api.ukuapi.com/api.php/provide/vod/?ac=list","searchable": 1,"categories": ["з»јиүә","еҠЁжј«","еҠЁдҪңзүҮ","е–ңеү§зүҮ","зҲұжғ…зүҮ","з§‘е№»зүҮ","жҒҗжҖ–зүҮ","еү§жғ…зүҮ","жҲҳдәүзүҮ","еӣҪдә§еү§","жёҜжҫіеү§","ж—Ҙеү§","ж¬§зҫҺеү§","еҠЁжј«з”өеҪұ","еҸ°ж№ҫеү§","йҹ©еү§","жі°еү§","и®°еҪ•зүҮ","зҹӯеү§","еҘҮе№»зүҮ","зҠҜзҪӘзүҮ"],"header": {"User-Agent": "Mozilla/5.0 (iPhone; CPU iPhone OS 15_2 like Mac OS X) AppleWebKit/605.1.15 (KHTML, like Gecko) Version/14.0 Mobile/15E148 Safari/604.1"}},
    {"key": "360иө„жәҗ","name": "еҪұи§Ҷ | 360иө„жәҗ[зӣҙиҝһ]","type": 1,"api": "https://360zy.com/api.php/provide/vod/?ac=list","searchable": 1,"categories": ["еҠЁдҪңзүҮ","е–ңеү§зүҮ","зҲұжғ…зүҮ","з§‘е№»зүҮ","жҒҗжҖ–зүҮ","еү§жғ…зүҮ","жҲҳдәүзүҮ","еӣҪдә§еү§","йҰҷжёҜеү§","йҹ©еӣҪеү§","ж¬§зҫҺеү§","NBA","жғҠжӮҡзүҮ","е®¶еәӯзҜҮ","еҸӨиЈ…зүҮ","еҺҶеҸІзүҮ","жӮ¬з–‘зүҮ","зҠҜзҪӘзүҮ","зҒҫйҡҫзүҮ","зәӘеҪ•зүҮ","зҹӯзүҮ","еҠЁз”»зүҮ","еҸ°ж№ҫеү§","ж—Ҙжң¬еү§","жө·еӨ–еү§","жі°еӣҪеү§","еӨ§йҷҶз»јиүә","жёҜеҸ°з»јиүә","ж—Ҙйҹ©з»јиүә","еӣҪдә§еҠЁжј«","ж¬§зҫҺеҠЁжј«","ж—Ҙйҹ©еҠЁжј«","иҘҝйғЁзүҮ","зҲҪж–Үзҹӯеү§","зҺ°д»ЈйғҪеёӮ","е№ҙд»Јз©ҝи¶Ҡ","еҸӨиЈ…д»ҷдҫ ","еҘійў‘жҒӢзҲұ","жҲҗй•ҝйҖҶиўӯ"],"header": {"User-Agent": "Mozilla/5.0 (iPhone; CPU iPhone OS 15_2 like Mac OS X) AppleWebKit/605.1.15 (KHTML, like Gecko) Version/14.0 Mobile/15E148 Safari/604.1"}},
    {"key": "жһҒйҖҹиө„жәҗ","name": "еҪұи§Ҷ | жһҒйҖҹ[зӣҙиҝһ]","type": 1,"api": "https://jszyapi.com/api.php/provide/vod/?ac=list","searchable": 1,"categories": ["ж¬§зҫҺеү§","йҰҷжёҜеү§","йҹ©еү§","ж—Ҙеү§","й©¬жі°еү§","еҠЁдҪңзүҮ","зҲұжғ…зүҮ","е–ңеү§зүҮ","з§‘е№»зүҮ","жҒҗжҖ–зүҮ","еү§жғ…зүҮ","жҲҳдәүзүҮ","и®°еҪ•зүҮ","еҠЁжј«","еҶ…ең°еү§","еҠЁз”»зүҮ","дёӯеӣҪеҠЁжј«","ж—Ҙжң¬еҠЁжј«"," ж¬§зҫҺеҠЁжј«","з»јиүә","еҸ°ж№ҫеү§","дҪ“иӮІиөӣдәӢ","еӨ§йҷҶз»јиүә","ж—Ҙйҹ©з»јиүә","жёҜеҸ°з»јиүә","ж¬§зҫҺз»јиүә","зҒҫйҡҫзүҮ","жӮ¬з–‘зүҮ","зҠҜзҪӘзүҮ","еҘҮе№»зүҮ","зҹӯеү§"],"header": {"User-Agent": "Mozilla/5.0 (iPhone; CPU iPhone OS 15_2 like Mac OS X) AppleWebKit/605.1.15 (KHTML, like Gecko) Version/14.0 Mobile/15E148 Safari/604.1"}},
    {"key": "зҺҮзҺҮ","name": "еҪұи§Ҷ | зҺҮзҺҮ[зӣҙиҝһ]","type": 1,"api": "https://suoniapi.com/api.php/provide/vod/?ac=list","searchable": 1,"quickSearch": 1,"changeable": 1,"categories": ["еӣҪдә§еү§","йҹ©еү§","ж—Ҙеү§","жёҜеү§","еҸ°еү§","еҠЁдҪңзүҮ","е–ңеү§зүҮ","зҲұжғ…зүҮ","з§‘е№»зүҮ","жҲҳдәүзүҮ","жҒҗжҖ–зүҮ","еү§жғ…зүҮ","еӣҪдә§еҠЁжј«","ж—Ҙйҹ©еҠЁжј«","ж¬§зҫҺеҠЁжј«","еӨ§йҷҶз»јиүә","ж—Ҙйҹ©з»јиүә"]},
    {"key": "зҷҫеәҰ","name": "зҷҫеәҰ","type": 1,"api": "https://api.apibdzy.com/api.php/provide/vod?ac=list","searchable": 1,"filterable": 0,"categories": ["еӣҪдә§еҠЁжј«","ж—Ҙйҹ©еҠЁжј«","еӨ§йҷҶеү§","ж¬§зҫҺеү§","йҹ©еү§","ж—Ҙеү§","еҠЁдҪңзүҮ","е–ңеү§зүҮ","зҲұжғ…зүҮ","з§‘е№»зүҮ","жҒҗжҖ–зүҮ","еү§жғ…зүҮ","жҲҳдәүзүҮ"],"header": {"User-Agent": "Mozilla/5.0"}},
    {"key": "жҡҙйўЁ","name": "еҪұи§Ҷ | жҡҙйўЁ[зӣҙиҝһ]","type": 1,"api": "https://bfzyapi.com/api.php/provide/vod/?ac=list","searchable": 1,"changeable": 1},
    {"key": "drpy_js_360еҪұи§Ҷ","name": "е®ҳжәҗ | 360[js]","type": 3,"api": "./lib/drpy2.min.js","ext": "./js/360еҪұи§Ҷ.js"},
    {"key": "drpy_js_зҷҫеҝҷж— жһң","name": "е®ҳжәҗ | иҠ’жһң[js]","type": 3,"api": "./lib/drpy2.min.js","ext": "./js/зҷҫеҝҷж— жһң.js"},
    {"key": "drpy_js_и…ҫдә‘й©ҫйӣҫ","name": "е®ҳжәҗ | и…ҫи®Ҝ[js]","type": 3,"api": "./lib/drpy2.min.js","ext": "./js/и…ҫдә‘й©ҫйӣҫ.js"},
    {"key": "drpy_js_еҘҮзҸҚејӮе…Ҫ","name": "е®ҳжәҗ | зҲұеҘҮиүә[js]","type": 3,"api": "./lib/drpy2.min.js","ext": "./js/еҘҮзҸҚејӮе…Ҫ.js"},
    {"key": "drpy_js_иҸңзӢ—","name": "е®ҳжәҗ | жҗңзӢ—[js]","type": 3,"api": "./lib/drpy2.min.js","ext": "./js/иҸңзӢ—.js"},
    {"key": "drpy_js_дјҳй…·","name": "е®ҳжәҗ | дјҳй…·[js]","type": 3,"api": "./lib/drpy2.min.js","ext": "./js/дјҳй…·.js"},
    {"key": "drpy_js_еҺӮй•ҝиө„жәҗ","name": "еҪұи§Ҷ | еҺӮй•ҝиө„жәҗ[js]","type": 3,"api": "./lib/drpy2.min.js","ext": "./js/еҺӮй•ҝиө„жәҗ.js","header": {"User-Agent": "Mozilla/5.0 (Windows NT 10.0; Win64; x64) AppleWebKit/537.36 (KHTML, like Gecko) Chrome/136.0.0.0 Safari/537.36 Edg/136.0.0.0"}},
    {"key": "drpy_js_58еҠЁжј«","name": "еҠЁжј« | 58еҠЁжј«[js]","type": 3,"api": "./lib/drpy2.min.js","ext": "./js/58еҠЁжј«.js"},
    {"key": "drpy_js_AGEеҠЁжј«","name": "еҠЁжј« | AGEеҠЁжј«[js]","type": 3,"api": "./lib/drpy2.min.js","ext": "./js/AGEеҠЁжј«.js"},
    {"key": "drpy_js_AnFuns","name": "еҠЁжј« | AnFuns[js]","type": 3,"api": "./lib/drpy2.min.js","ext": "./js/AnFuns.js"},
    {"key": "drpy_js_Anime1еҠЁз•«","name": "еҠЁжј« | Anime1еҠЁз•«[js]","type": 3,"api": "./lib/drpy2.min.js","ext": "./js/Anime1еҠЁз•«.js"},
    {"key": "drpy_js_NTеҠЁжј«","name": "еҠЁжј« | NTеҠЁжј«[js]","type": 3,"api": "./lib/drpy2.min.js","ext": "./js/NTеҠЁжј«.js"},
    {"key": "drpy_js_NyaFun","name": "еҠЁжј« | NyaFun[js]","type": 3,"api": "./lib/drpy2.min.js","ext": "./js/NyaFun.js"},
    {"key": "drpy_js_зҲұеј№е№•","name": "еҠЁжј« | зҲұеј№е№•[js]","type": 3,"api": "./lib/drpy2.min.js","ext": "./js/зҲұеј№е№•.js"},
    {"key": "drpy_js_еҠЁжј«еІӣ","name": "еҠЁжј« | еҠЁжј«еІӣ[js]","type": 3,"api": "./lib/drpy2.min.js","ext": "./js/еҠЁжј«еІӣ.js"},
    {"key": "drpy_js_и·Ҝжј«жј«","name": "еҠЁжј« | и·Ҝжј«жј«[js]","type": 3,"api": "./lib/drpy2.min.js","ext": "./js/и·Ҝжј«жј«.js"},
    {"key": "drpy_js_е–өж¬Ўе…ғ","name": "еҪұи§Ҷ | е–өж¬Ўе…ғ[js]","type": 3,"api": "./lib/drpy2.min.js","ext": "./js/е–өж¬Ўе…ғ.js"},
    {"key": "drpy_js_еҘҮзұіеҠЁжј«","name": "еҠЁжј« | еҘҮзұіеҠЁжј«[js]","type": 3,"api": "./lib/drpy2.min.js","ext": "./js/еҘҮзұіеҠЁжј«.js"},
    {"key": "drpy_js_еҺ»зңӢеҗ§","name": "еҠЁжј« | еҺ»зңӢеҗ§[js]","type": 3,"api": "./lib/drpy2.min.js","ext": "./js/еҺ»зңӢеҗ§.js"},
    {"key": "drpy_js_жӣІеҘҮеҠЁжј«","name": "еҠЁжј« | жӣІеҘҮеҠЁжј«[js]","type": 3,"api": "./lib/drpy2.min.js","ext": "./js/жӣІеҘҮеҠЁжј«.js"},
    {"key": "drpy_js_ејӮдё–з•ҢеҠЁжј«жј«","name": "еҠЁжј« | ејӮдё–з•ҢеҠЁжј«[js]","type": 3,"api": "./lib/drpy2.min.js","ext": "./js/ејӮдё–з•ҢеҠЁжј«.js"},
    {"key": "drpy_js_жҖЎиҗұеҠЁжј«","name": "еҠЁжј« | жҖЎиҗұеҠЁжј«[js]","type": 3,"api": "./lib/drpy2.min.js","ext": "./js/жҖЎиҗұеҠЁжј«.js"},
    {"key": "drpy_js_A8йҹід№җ","name": "йҹійў‘ | A8йҹід№җ[js]","type": 3,"api": "./lib/drpy2.min.js","ext": "./js/A8йҹід№җ.js"},
    {"key": "drpy_js_DJйҹід№җ","name": "йҹійў‘ | DJйҹід№җ[js]","type": 3,"api": "./lib/drpy2.min.js","changeable": 0,"style": {"type": "rect","ratio": 1},"ext": "./js/DJйҹід№җ.js"},
    {"key": "drpy_js_е•Ұе•ҰDJ","name": "йҹійў‘ | е•Ұе•ҰDJ[js]","type": 3,"api": "./lib/drpy2.min.js","changeable": 0,"style": {"type": "rect","ratio": 1},"ext": "./js/е•Ұе•ҰDJ.js"},
    {"key": "drpy_js_жё…йЈҺDJ","name": "йҹійў‘ | жё…йЈҺDJ[js]","type": 3,"api": "./lib/drpy2.min.js","changeable": 0,"style": {"type": "rect","ratio": 1},"ext": "./js/жё…йЈҺDJ.js"},
    {"key": "drpy_js_е№ҝж’ӯиҝ·FM","name": "е№ҝж’ӯ | е№ҝж’ӯиҝ·FM[js]","type": 3,"api": "./lib/drpy2.min.js","changeable": 0,"ext": "./js/е№ҝж’ӯиҝ·FM.js"},
    {"key": "drpy_js_иң»иң“FM","name": "е№ҝж’ӯ | иң»иң“FM[js]","type": 3,"api": "./lib/drpy2.min.js","changeable": 0,"ext": "./js/иң»иң“FM.js"},
    {"key": "drpy_js_i275еҗ¬д№Ұ","name": "еҗ¬д№Ұ | i275еҗ¬д№Ұ[js]","type": 3,"api": "./lib/drpy2.min.js","changeable": 0,"style": {"type": "rect","ratio": 1},"ext": "./js/i275еҗ¬д№Ұ.js"},
    {"key": "drpy_js_зҲұдёҠдҪ еҗ¬д№ҰзҪ‘","name": "еҗ¬д№Ұ | зҲұдёҠдҪ еҗ¬д№Ұ[js]","type": 3,"api": "./lib/drpy2.min.js","changeable": 0,"style": {"type": "rect","ratio": 1},"ext": "./js/зҲұдёҠдҪ еҗ¬д№ҰзҪ‘.js"},
    {"key": "drpy_js_еҚҡзңӢеҗ¬д№Ұ","name": "еҗ¬д№Ұ | еҚҡзңӢеҗ¬д№Ұ[js]","type": 3,"api": "./lib/drpy2.min.js","changeable": 0,"style": {"type": "rect","ratio": 1},"ext": "./js/еҚҡзңӢеҗ¬д№Ұ.js"},
    {"key": "drpy_js_жө·жҙӢеҗ¬д№Ұ","name": "еҗ¬д№Ұ | жө·жҙӢеҗ¬д№Ұ[js]","type": 3,"api": "./lib/drpy2.min.js","changeable": 0,"style": {"type": "rect","ratio": 1},"ext": "./js/жө·жҙӢеҗ¬д№Ұ.js"},
    {"key": "drpy_js_е…ӯжңҲеҗ¬д№Ұ","name": "еҗ¬д№Ұ | е…ӯжңҲеҗ¬д№Ұ[js]","type": 3,"api": "./lib/drpy2.min.js","changeable": 0,"style": {"type": "rect","ratio": 1},"ext": "./js/е…ӯжңҲеҗ¬д№Ұ.js"},
    {"key": "drpy_js_жңүеЈ°е°ҸиҜҙ","name": "еҗ¬д№Ұ | жңүеЈ°е°ҸиҜҙ[js]","type": 3,"api": "./lib/drpy2.min.js","changeable": 0,"style": {"type": "rect","ratio": 1},"ext": "./js/жңүеЈ°е°ҸиҜҙеҗ§.js"},
    {"key": "drpy_js_ж’ӯе®ў","name": "иҒҡеҗҲ | ж’ӯе®ў[js]","type": 3,"api": "./lib/drpy2.min.js","ext": "./js/ж’ӯе®ў.js"},
    {"key": "drpy_js_зҹӯи§Ҷйў‘","name": "иҒҡеҗҲ | зҹӯи§Ҷйў‘[js]","type": 3,"api": "./lib/drpy2.min.js","changeable": 0,"ext": "./js/зҹӯи§Ҷйў‘.js"},
    {"key": "drpy_js_й…·6зҪ‘","name": "иҒҡеҗҲ | й…·6зҪ‘[js]","type": 3,"api": "./lib/drpy2.min.js","changeable": 0,"ext": "./js/й…·6зҪ‘.js"},
    {"key": "drpy_js_зҪ‘жҳ“е…¬зүҲеҪұеғҸ","name": "иҒҡеҗҲ | зҪ‘жҳ“е…¬зүҲ[js]","type": 3,"api": "./lib/drpy2.min.js","changeable": 0,"style": {"type": "rect","ratio": 1.597},"ext": "./js/зҪ‘жҳ“е…¬зүҲеҪұеғҸ.js"},
    {"key": "drpy_js_зҲұиҪҰMV","name": "MV | зҲұиҪҰMV[js]","type": 3,"api": "./lib/drpy2.min.js","changeable": 0,"style": {"type": "rect","ratio": 1},"ext": "./js/зҲұиҪҰMV.js"},
    {"key": "drpy_js_й…·еҘҮMV","name": "MV | й…·еҘҮ[js]","type": 3,"api": "./lib/drpy2.min.js","changeable": 0,"style": {"type": "rect","ratio": 1},"ext": "./js/й…·еҘҮMV.js"},
    {"key": "жҮүз”Ёе•Ҷеә—","name": "жҮүз”Ёе•Ҷеә—","type": 3,"api": "csp_Market","searchable": 0,"changeable": 0,"ext": "./json/market.json","jar": "./jar/pg.jar"},
    {"key": "bb","name": "й…ҚзҪ®жҺҘеҸЈе®Ңе…Ёе…Қиҙ№","type": 3,"api": "./lib/drpy2.min.js","ext": "./js/drpy.js"},
    {"key": "cc","name": "иҜ·еӢҝзӣёдҝЎи§Ҷйў‘дёӯд»»дҪ•е№ҝе‘Ҡ","type": 3,"api": "./lib/drpy2.min.js","ext": "./js/drpy.js"}
  ],
  "parses": [
    {"name": "JsonиҒҡеҗҲ","type": 3,"url": "Demo"},
    {"name": "jx","type": 0,"url": "https://jx.m3u8.tv/jx/jx.php?url="},
    {"name": "зҫҪи·ҜеқҮжІҫ","type": 0,"url": "https://ylu.cc/index.php?url="},
    {"name": "999","type": 0,"url": "https://huayong.net/999/?v="},
    {"name": "jx5","type": 0,"url": "https://huayong.net/jx5/?url="},
    {"name": "ж— е°Ҫ","type": 0,"url": "https://jx.wujinkk.com/dplayer/?url=","ext": {"header": {"User-Agent": "Mozilla/5.0"}}},
    {"name": "yemu","type": 0,"url": "https://www.yemu.xyz/?url="},
    {"name": "и§Јжһҗ1","type": 0,"url": "https://bd.jx.cn/?url="},
    {"name": "и§Јжһҗ2","type": 0,"url": "https://jx.m3u8.tv/jiexi/?url="},
    {"name": "и§Јжһҗ3","type": 0,"url": "https://player.mrgaocloud.com/player/?url="},
    {"name": "vip4","type": 0,"url": "https://huayong.net/vip4/?url="},
    {"name": "е…Қиҙ№еҲҶдә«","type": 0,"url": "https://jx.xmflv.com/?url=","ext": {"flag": ["qq","и…ҫи®Ҝ","qiyi","зҲұеҘҮиүә","еҘҮиүә","youku","дјҳй…·","mgtv","иҠ’жһң","imgo","letv","д№җи§Ҷ","pptv","PPTV","sohu","bilibili","е“”е“©е“”е“©","е“”е“©"],"header": {"User-Agent": "okhttp/4.1.0"}}},
    {"name": "е…Ёж°‘","url": "http://api.wpsseo.cn/?v=","type": 0,"ext": {"flag": ["qiyi","imgo","зҲұеҘҮиүә","еҘҮиүә","qq","и…ҫи®Ҝ","youku","дјҳй…·","pptv","PPTV","letv","д№җи§Ҷ","leshi","bilibili","е“”е“©е“”е“©","е“”е“©","mgtv","иҠ’жһң","sohu","xigua","fun","йЈҺиЎҢ"],"header": {"User-Agent": "Mozilla/5.0"}}},
    {"name": "m3u8","type": 0,"url": "https://jx.m3u8.tv/jiexi/?url="},
    {"name": "8090","url": "https://www.8090.la/lander?url=","type": 0,"ext": {"flag": ["qiyi","imgo","зҲұеҘҮиүә","еҘҮиүә","qq","и…ҫи®Ҝ","youku","дјҳй…·","pptv","PPTV","letv","д№җи§Ҷ","leshi","bilibili","е“”е“©е“”е“©","е“”е“©","mgtv","иҠ’жһң","sohu","xigua","fun","йЈҺиЎҢ"],"header": {"User-Agent": "Mozilla/5.0"}}},
    {"name": "зңӢзңӢ","type": 0,"url": "https://jx.m3u8.pw/?url="},
    {"name": "е·§жҠҖ","type": 1,"url": "http://pandown.pro/app/kkdy.php?url=","ext": {"flag": ["qq","и…ҫи®Ҝ","qiyi","зҲұеҘҮиүә","еҘҮиүә","youku","дјҳй…·","sohu","жҗңзӢҗ","letv","д№җи§Ҷ","mgtv","иҠ’жһң","rx","ltnb","bilibili","1905","xigua"]}},
    {"name": "е·ҰеІё","type": 1,"url": "https://api.tyun77.cn/api.php/provide/parseDicturl?url=","ext": {"flag": ["зҲұеҘҮиүә","еҘҮиүә","qq","и…ҫи®Ҝ","youku","дјҳй…·","pptv","PPTV","letv","д№җи§Ҷ","leshi","bilibili","е“”е“©е“”е“©","е“”е“©","mgtv","иҠ’жһң","иҠ’жһң"],"header": {"User-Agent": "okhttp/3.12.0"}}},
    {"name": "е’ёйұј","type": 0,"url": "https://jx.xymp4.cc/?url=","ext": {"header": {"user-agent": "Mozilla/5.0(Linux;Android13;V2049ABuild/TP1A.220624.014;wv)AppleWebKit/537.36(KHTML,likeGecko)Version/4.0Chrome/116.0.0.0MobileSafari/537.36","referer": "https://www.xyflv.cc/"}}},
    {"name": "ж— дёҠ","type": "1","url": "https://mfjx.iwsyy.xyz/?url=","ext": {"flag": ["qq","и…ҫи®Ҝ","qiyi","зҲұеҘҮиүә","еҘҮиүә","youku","дјҳй…·","sohu","жҗңзӢҗ","letv","д№җи§Ҷ","mgtv","иҠ’жһң","tnmb","seven","bilibili","1905"],"header": {"User-Agent": "okhttp/4.9.1"}}},
    {"name": "е·§и®Ў","type": 1,"url": "https://zy.qiaoji8.com/xiafan.php?url=","ext": {"flag": ["QD4K","iyf","duanju","gzcj","GTV","GZYS","weggz","Ace"],"header": {"User-Agent": "okhttp/4.9.1"}}},
    {"name": "иҷҫзұі","type": 0,"url": "https://jx.xmflv.com/?url=","ext": {"header": {"user-agent": "Mozilla/5.0(WindowsNT10.0;Win64;x64)AppleWebKit/537.36(KHTML,likeGecko)Chrome/110.0.0.0Safari/537.36Edg/110.0.1587.57"}}},
    {"name": "ж·ҳзүҮ","type": 0,"url": "https://jx.yparse.com/index.php?url=","ext": {"header": {"user-agent": "Mozilla/5.0(Linux;Android13;V2049ABuild/TP1A.220624.014;wv)AppleWebKit/537.36(KHTML,likeGecko)Version/4.0Chrome/116.0.0.0MobileSafari/537.36"}}},
    {"name": "еҶ°иұҶ","type": 0,"url": "https://bd.jx.cn/?url=","ext": {"header": {"user-agent": "Mozilla/5.0(Linux;Android13;V2049ABuild/TP1A.220624.014;wv)AppleWebKit/537.36(KHTML,likeGecko)Version/4.0Chrome/116.0.0.0MobileSafari/537.36"}}},
    {"name": "дёғдёғ","type": 0,"url": "https://jx.77flv.cc/?url=","ext": {"header": {"user-agent": "Mozilla/5.0(Linux;Android13;V2049ABuild/TP1A.220624.014;wv)AppleWebKit/537.36(KHTML,likeGecko)Version/4.0Chrome/116.0.0.0MobileSafari/537.36"}}},
    {"name": "зӣҳеҸӨ","type": 0,"url": "https://www.playm3u8.cn/jiexi.php?url=","ext": {"header": {"user-agent": "Mozilla/5.0(Linux;Android13;V2049ABuild/TP1A.220624.014;wv)AppleWebKit/537.36(KHTML,likeGecko)Version/4.0Chrome/116.0.0.0MobileSafari/537.36"}}},
    {"name": "еӨңе№•","type": 0,"url": "https://yemu.xyz/?url=","ext": {"header": {"user-agent": "Mozilla/5.0(Linux;Android13;V2049ABuild/TP1A.220624.014;wv)AppleWebKit/537.36(KHTML,likeGecko)Version/4.0Chrome/116.0.0.0MobileSafari/537.36"}}},
    {"name": "дә‘и§Јжһҗ","type": 0,"url": "https://jx.yparse.com/index.php?url=","ext": {"header": {"user-agent": "Mozilla/5.0(Linux;Android13;V2049ABuild/TP1A.220624.014;wv)AppleWebKit/537.36(KHTML,likeGecko)Version/4.0Chrome/116.0.0.0MobileSafari/537.36"}}}
  ],
  "hosts": ["cache.ott.ystenlive.itv.cmvideo.cn=base-v4-free-mghy.e.cdn.chinamobile.com", "cache.ott.bestlive.itv.cmvideo.cn=base-v4-free-mghy.e.cdn.chinamobile.com", "cache.ott.wasulive.itv.cmvideo.cn=base-v4-free-mghy.e.cdn.chinamobile.com", "cache.ott.fifalive.itv.cmvideo.cn=base-v4-free-mghy.e.cdn.chinamobile.com", "cache.ott.hnbblive.itv.cmvideo.cn=base-v4-free-mghy.e.cdn.chinamobile.com"],
  "flags": ["youku", "дјҳй…·", "дјҳ й…·", "дјҳй…·и§Ҷйў‘", "qq", "и…ҫи®Ҝ", "и…ҫ и®Ҝ", "и…ҫи®Ҝи§Ҷйў‘", "iqiyi", "qiyi", "еҘҮиүә", "зҲұеҘҮиүә", "зҲұ еҘҮ иүә", "m1905", "xigua", "letv", "leshi", "д№җи§Ҷ", "д№җ и§Ҷ", "sohu", "жҗңзӢҗ", "жҗң зӢҗ", "жҗңзӢҗи§Ҷйў‘", "tudou", "mgtv", "иҠ’жһң", "imgo", "иҠ’жһңTV", "иҠ’ жһң T V", "bilibili", "е“” е“©", "е“” е“© е“” е“©", "SPA", "YuMi-vip", "pptv", "PPTV", "ltnb", "rx", "SLYS4k", "tucheng", "BYGA", "luanzi", "dxzy", "QEYSS", "aliyun", "AliS", "122", "chuangying", "CL4K", "xfyun", "wuduzy", "wasu", "renrenmi", "ppayun", "haiwaikan", "cool", "dbm3u8", "xmm", "funshion", "ruyi1080", "ruyib1080"],
  "doh": [
    {"name": "Google","url": "https://dns.google/dns-query","ips": ["8.8.4.4","8.8.8.8"]},
    {"name": "Cloudflare","url": "https://cloudflare-dns.com/dns-query","ips": ["1.1.1.1","1.0.0.1","2606:4700:4700::1111","2606:4700:4700::1001"]},
    {"name": "AdGuard","url": "https://dns.adguard.com/dns-query","ips": ["94.140.14.140","94.140.14.141"]},
    {"name": "DNSWatch","url": "https://resolver2.dns.watch/dns-query","ips": ["84.200.69.80","84.200.70.40"]},
    {"name": "Quad9","url": "https://dns.quad9.net/dns-query","ips": ["9.9.9.9","149.112.112.112"]}
  ],
  "rules": [
    {"name": "proxy","hosts": ["mypikpak.com",".*workers.dev","www.cilixiong.com","*.t4tv.hz.cz","kuba222.com","mp4us.com","dydhhy.com","magicalsearch.top","api123.adys.app","raw.githubusercontent.com","googlevideo.com","cdn.v82u1l.com","cdn.iz8qkg.com","cdn.kin6c1.com","c.biggggg.com","c.olddddd.com","haiwaikan.com","www.histar.tv","youtube.com","uhibo.com",".*boku.*",".*nivod.*",".*ulivetv.*"]},
    {"name": "зЈҒеҠӣе»Је‘Ҡ","hosts": ["magnet"],"regex": ["жӣҙеӨҡ","зӨҫеҚҖ","xuu","жңҖж–°","жңҖж–°","зӣҙж’ӯ","жӣҙж–°","зӨҫеҢә","жңүи¶Ј","жңүи¶Ј","иӢұзҡҮдҪ“иӮІ","е…Ёдёӯж–ҮAVеңЁзәҝ","жҫій—ЁзҡҮеҶ иөҢеңә","е“Ҙе“Ҙеҝ«жқҘ","зҫҺеҘіиҚ·е®ҳ","иЈёиҒҠ","ж–°зүҮйҰ–еҸ‘","UUE29"]},
    {"name": "жө·еӨ–зңӢ","hosts": ["haiwaikan"],"regex": ["8.16","8.1748","10.0099","10.3333","10.85","12.33","16.0599"]},
    {"name": "зҙўе°ј","hosts": ["suonizy"],"regex": ["15.1666","15.2666"]},
    {"name": "жҳҹжҳҹ","hosts": ["aws.ulivetv.net"],"regex": ["#EXT-X-DISCONTINUITY\\r*\\n*#EXTINF:8,[\\s\\S]*?#EXT-X-DISCONTINUITY"]},
    {"name": "йҮҸеӯҗе№ҝе‘Ҡ","hosts": ["vip.lz*","hd.lz*",".cdnlz",".cdnlz*"],"regex": ["#EXTINF.*?\\s+[a-z0-9]{18,}\\.ts","[a-z0-9]{18,}\\.ts\\s+","#EXT-X-DISCONTINUITY\\r*\\n*#EXTINF.*?\\s+[a-z0-9]{18,}\\.ts[\\s\\S]*?#EXT-X-DISCONTINUITY"]},
    {"name": "йқһеҮЎе№ҝе‘Ҡ","hosts": ["vip.ffzy","hd.ffzy",".ffzy*","super.ffzy","super.ffzy*","svipsvip.ffzy","*.ffzy*"],"regex": ["#EXT-X-DISCONTINUITY(?:\n.*?){8}\n#EXT-X-DISCONTINUITY","#EXT-X-DISCONTINUITY(?:\n(?!#EXT-X-DISCONTINUITY).*){10}\n#EXT-X-DISCONTINUITY"]},
    {"name": "qihubf","hosts": ["qihubf"],"regex": ["#EXT-X-DISCONTINUITY\\r*\\n*#EXT-X-KEY:METHOD=NONE\\r*\\n*#EXTINF:2,[\\s\\S]*?#EXT-X-DISCONTINUITY\\r*\\n*#EXT-X-KEY:METHOD=AES-128","#EXT-X-DISCONTINUITY\\r*\\n*#EXT-X-KEY:METHOD=NONE\\r*\\n*#EXTINF:2,[\\s\\S]*?#EXT-X-DISCONTINUITY"]},
    {"name": "еҝ«зңӢе№ҝе‘Ҡ","hosts": ["kuaikan"],"regex": ["#EXT-X-DISCONTINUITY\\r*\\n*#EXT-X-KEY:METHOD=NONE\\r*\\n*#EXTINF:.*?,[\\s\\S]*?#EXT-X-DISCONTINUITY"]},
    {"name": "Uй…·иө„жәҗе№ҝе‘Ҡ","hosts": ["ukzy"],"regex": ["#EXT-X-DISCONTINUITY\\r*\\n*#EXT-X-KEY:METHOD=NONE\\r*\\n*#EXTINF:.*?,[\\s\\S]*?#EXT-X-DISCONTINUITY"]},
    {"name": "ikunиө„жәҗ","hosts": ["bfikuncdn"],"regex": ["#EXT-X-DISCONTINUITY\\r*\\n*#EXT-X-KEY:METHOD=NONE\\r*\\n*#EXTINF:.*?,[\\s\\S]*?#EXT-X-DISCONTINUITY"]},
    {"name": "еҚ§йҫҷеҪұи§Ҷиө„жәҗ","hosts": ["cdn.wl*"],"regex": ["#EXT-X-DISCONTINUITY\\r*\\n*#EXTINF:.*?,[\\s\\S]*?#EXT-X-DISCONTINUITY"]},
    {"name": "жҡҙйЈҺе№ҝе‘Ҡ","hosts": ["bfzy","bfbfvip","bfengbf"],"regex": ["#EXTINF.*?\\s+.*?adjump.*?\\.ts\\s+"]},
    {"name": "зҒ«еұұе—…жҺў","hosts": ["huoshan.com"],"regex": ["item_id="]},
    {"name": "жҠ–йҹіе—…жҺў","hosts": ["douyin.com"],"regex": ["is_play_url="]},
    {"name": "иҫІж°‘е—…жҺў","hosts": ["toutiaovod.com"],"regex": ["video/tos/cn"]},
    {"name": "дёғж–°е—…жҺў","hosts": ["api.52wyb.com"],"regex": ["m3u8?pt=m3u8"]},
    {"name": "еӨңеёӮй»һж“Ҡ","hosts": ["yeslivetv.com"],"script": ["document.getElementsByClassName('vjs-big-play-button')[0].click()"]},
    {"name": "жҜӣй©ўй»һж“Ҡ","hosts": ["www.maolvys.com"],"script": ["document.getElementsByClassName('swal-buttonswal-button--confirm')[0].click()"]}
  ],
  "ads": ["mimg.0c1q0l.cn", "www.googletagmanager.com", "www.google-analytics.com", "mc.usihnbcq.cn", "mg.g1mm3d.cn", "mscs.svaeuzh.cn", "cnzz.hhttm.top", "tp.vinuxhome.com", "cnzz.mmstat.com", "www.baihuillq.com", "s23.cnzz.com", "z3.cnzz.com", "c.cnzz.com", "stj.v1vo.top", "z12.cnzz.com", "img.mosflower.cn", "tips.gamevvip.com", "ehwe.yhdtns.com", "xdn.cqqc3.com", "www.jixunkyy.cn", "sp.chemacid.cn", "hm.baidu.com", "s9.cnzz.com", "z6.cnzz.com", "um.cavuc.com", "mav.mavuz.com", "wofwk.aoidf3.com", "z5.cnzz.com", "xc.hubeijieshikj.cn", "tj.tianwenhu.com", "xg.gars57.cn", "k.jinxiuzhilv.com", "cdn.bootcss.com", "ppl.xunzhuo123.com", "xomk.jiangjunmh.top", "img.xunzhuo123.com", "z1.cnzz.com", "s13.cnzz.com", "xg.huataisangao.cn", "z7.cnzz.com", "xg.huataisangao.cn", "z2.cnzz.com", "s96.cnzz.com", "q11.cnzz.com", "thy.dacedsfa.cn", "xg.whsbpw.cn", "s19.cnzz.com", "z8.cnzz.com", "s4.cnzz.com", "f5w.as12df.top", "ae01.alicdn.com", "www.92424.cn", "k.wudejia.com", "vivovip.mmszxc.top", "qiu.xixiqiu.com", "cdnjs.hnfenxun.com", "cms.qdwght.com", "iqiyi.hbuioo.com", "vip.ffzyad.com", "wan.51img1.com", "https://lf1-cdn-tos.bytegoofy.com/obj/tos-cn-i-dy/455ccf9e8ae744378118e4bd289288dd", "mimg.0c1q0l.cn", "www.googletagmanager.com", "www.google-analytics.com", "mc.usihnbcq.cn", "mg.g1mm3d.cn", "mscs.svaeuzh.cn", "cnzz.hhttm.top", "tp.vinuxhome.com", "cnzz.mmstat.com", "www.baihuillq.com", "s23.cnzz.com", "z3.cnzz.com", "c.cnzz.com", "stj.v1vo.top", "z12.cnzz.com", "img.mosflower.cn", "tips.gamevvip.com", "ehwe.yhdtns.com", "xdn.cqqc3.com", "www.jixunkyy.cn", "sp.chemacid.cn", "hm.baidu.com", "s9.cnzz.com", "z6.cnzz.com", "um.cavuc.com", "mav.mavuz.com", "wofwk.aoidf3.com", "z5.cnzz.com", "xc.hubeijieshikj.cn", "tj.tianwenhu.com", "xg.gars57.cn", "k.jinxiuzhilv.com", "cdn.bootcss.com", "ppl.xunzhuo123.com", "xomk.jiangjunmh.top", "img.xunzhuo123.com", "z1.cnzz.com", "s13.cnzz.com", "xg.huataisangao.cn", "z7.cnzz.com", "xg.huataisangao.cn", "z2.cnzz.com", "s96.cnzz.com", "q11.cnzz.com", "thy.dacedsfa.cn", "xg.whsbpw.cn", "s19.cnzz.com", "z8.cnzz.com", "s4.cnzz.com", "f5w.as12df.top", "ae01.alicdn.com", "www.92424.cn", "k.wudejia.com", "vivovip.mmszxc.top", "qiu.xixiqiu.com", "cdnjs.hnfenxun.com", "cms.qdwght.com"]
}